django_future_staticfiles/storage.py
django_future_staticfiles/__init__.py
tests/staticfiles_tests/signals.py
tests/staticfiles_tests/tests.py
tests/staticfiles_tests/storage.py
tests/staticfiles_tests/__init__.py
tests/staticfiles_tests/urls/helper.py
tests/staticfiles_tests/urls/default.py
tests/staticfiles_tests/urls/__init__.py
tests/staticfiles_tests/apps/__init__.py
tests/staticfiles_tests/apps/test/__init__.py
tests/staticfiles_tests/apps/no_label/__init__.py
django_future_staticfiles-0.1.0.dist-info/RECORD
django_future_staticfiles-0.1.0.dist-info/top_level.txt
django_future_staticfiles-0.1.0.dist-info/WHEEL
django_future_staticfiles-0.1.0.dist-info/METADATA
django_future_staticfiles-0.1.0.dist-info/metadata.json
django_future_staticfiles-0.1.0.dist-info/DESCRIPTION.rst
