Metadata-Version: 2.0
Name: django-future-staticfiles
Version: 0.1.0
Summary: Backport of Django staticfiles storages from Django 1.7+ to earlier Django 1.6
Home-page: https://github.com/dsanders11/django-future-staticfiles/
Author: David Sanders
Author-email: dsanders11@ucsbalum.com
License: MIT
Keywords: django staticfiles future
Platform: UNKNOWN
Classifier: Development Status :: 4 - Beta
Classifier: Environment :: Web Environment
Classifier: Framework :: Django
Classifier: Intended Audience :: Developers
Classifier: License :: OSI Approved :: MIT License
Classifier: Operating System :: OS Independent
Classifier: Programming Language :: Python
Classifier: Programming Language :: Python :: 2.6
Classifier: Programming Language :: Python :: 2.7
Classifier: Programming Language :: Python :: 3.2
Classifier: Programming Language :: Python :: 3.3
Classifier: Programming Language :: Python :: 3.4
Classifier: Topic :: Utilities
Requires-Dist: Django (>=1.6)
